sidematter_format/__init__.py
sidematter_format/json_conventions.py
sidematter_format/py.typed
sidematter_format/sidematter_format.py
sidematter_format/sidematter_utils.py
sidematter_format/yaml_conventions.py
sidematter_format-0.0.5.dist-info/METADATA
sidematter_format-0.0.5.dist-info/WHEEL
sidematter_format-0.0.5.dist-info/entry_points.txt
sidematter_format-0.0.5.dist-info/licenses/LICENSE
sidematter_format-0.0.5.dist-info/RECORD
