Metadata-Version: 2.4
Name: sidematter-format
Version: 0.0.5
Summary: A convention for metadata and asset files alongside any document
Project-URL: Repository, https://github.com/jlevy/sidematter-format
Author-email: Joshua Levy <joshua@cal.berkeley.edu>
License-Expression: MIT
License-File: LICENSE
Classifier: Development Status :: 4 - Beta
Classifier: Intended Audience :: Developers
Classifier: License :: OSI Approved :: MIT License
Classifier: Operating System :: OS Independent
Classifier: Programming Language :: Python
Classifier: Programming Language :: Python :: 3
Classifier: Programming Language :: Python :: 3.10
Classifier: Programming Language :: Python :: 3.11
Classifier: Programming Language :: Python :: 3.12
Classifier: Programming Language :: Python :: 3.13
Classifier: Typing :: Typed
Requires-Python: <4.0,>=3.10
Requires-Dist: frontmatter-format>=0.2.3
Requires-Dist: strif>=3.0.1
